pngquant/__init__.py
pngquant/compat.py
pngquant/main.py
pngquant-3.0.3.dist-info/METADATA
pngquant-3.0.3.dist-info/WHEEL
pngquant-3.0.3.dist-info/top_level.txt
pngquant-3.0.3.dist-info/RECORD
